{"name":"插件","postlist":[{"title":"Hexo博客 | 插件推荐","slug":"博客相关-Hexo插件推荐","date":"2020-07-12T13:02:30.000Z","updated":"2020-07-12T13:02:30.000Z","comments":true,"path":"api/articles/博客相关-Hexo插件推荐.json","excerpt":null,"keywords":null,"cover":"https://unpkg.com/justlovesmile-img/224324-158886260488d3.jpg","content":null,"raw":null,"categories":[{"name":"博客相关","path":"api/categories/博客相关.json"}],"tags":[{"name":"Hexo","path":"api/tags/Hexo.json"},{"name":"插件","path":"api/tags/插件.json"}]},{"title":"Hexo博客 | Hexo竟然可以展示PDF","slug":"博客相关-Hexo竟然可以展示PDF","date":"2020-07-03T09:06:02.000Z","updated":"2020-07-03T09:06:02.000Z","comments":true,"path":"api/articles/博客相关-Hexo竟然可以展示PDF.json","excerpt":null,"keywords":null,"cover":"https://unpkg.com/justlovesmile-img/20200703173123.png","content":null,"raw":null,"categories":[{"name":"博客相关","path":"api/categories/博客相关.json"}],"tags":[{"name":"Hexo","path":"api/tags/Hexo.json"},{"name":"插件","path":"api/tags/插件.json"}]},{"title":"Hexo博客 | 加密！给你的文章添加密码","slug":"博客相关-Hexo添加博客加密功能","date":"2019-09-04T15:20:00.000Z","updated":"2019-09-04T15:20:00.000Z","comments":true,"path":"api/articles/博客相关-Hexo添加博客加密功能.json","excerpt":null,"keywords":null,"cover":"https://unpkg.com/justlovesmile-img/224809-1574261289b9bb.jpg","content":null,"raw":null,"categories":[{"name":"博客相关","path":"api/categories/博客相关.json"}],"tags":[{"name":"Hexo","path":"api/tags/Hexo.json"},{"name":"插件","path":"api/tags/插件.json"}]}]}