{"name":"旅拍","postlist":[{"title":"生活VLOG | 哈尔滨的春雪","slug":"生活琐事-哈尔滨的春雪vlog","date":"2020-03-12T15:52:13.000Z","updated":"2020-03-12T15:52:13.000Z","comments":true,"path":"api/articles/生活琐事-哈尔滨的春雪vlog.json","excerpt":null,"keywords":null,"cover":"https://cdn.jsdelivr.net/gh/Justlovesmile/CDN/image/194038-1582544438d97b.jpg","content":null,"raw":null,"categories":[{"name":"生活琐事","path":"api/categories/生活琐事.json"}],"tags":[{"name":"生活","path":"api/tags/生活.json"},{"name":"旅拍","path":"api/tags/旅拍.json"},{"name":"vlog","path":"api/tags/vlog.json"}]},{"title":"生活VLOG |  一个人说走就走的旅行","slug":"生活琐事-一个人说走就走的旅行","date":"2020-06-01T15:40:41.000Z","updated":"2020-06-01T15:40:41.000Z","comments":true,"path":"api/articles/生活琐事-一个人说走就走的旅行.json","excerpt":null,"keywords":null,"cover":"https://cdn.jsdelivr.net/gh/Justlovesmile/CDN/image/212112-155179207249ae.jpg","content":null,"raw":null,"categories":[{"name":"生活琐事","path":"api/categories/生活琐事.json"}],"tags":[{"name":"生活","path":"api/tags/生活.json"},{"name":"旅拍","path":"api/tags/旅拍.json"},{"name":"vlog","path":"api/tags/vlog.json"}]},{"title":"生活VLOG | 滑雪旅拍，北境踏雪","slug":"生活琐事-滑雪旅拍-北境踏雪","date":"2020-03-24T03:55:06.000Z","updated":"2020-03-24T03:55:06.000Z","comments":true,"path":"api/articles/生活琐事-滑雪旅拍-北境踏雪.json","excerpt":null,"keywords":null,"cover":"https://cdn.jsdelivr.net/gh/Justlovesmile/CDN/image/6318a55feeceb172b43b4063722fa85.jpg","content":null,"raw":null,"categories":[{"name":"生活琐事","path":"api/categories/生活琐事.json"}],"tags":[{"name":"生活","path":"api/tags/生活.json"},{"name":"旅拍","path":"api/tags/旅拍.json"},{"name":"vlog","path":"api/tags/vlog.json"}]}]}